safehouse/__init__.py
safehouse/assertions.py
safehouse/mode.py
safehouse/types.py
safehouse/apps/__init__.py
safehouse/apps/console/__init__.py
safehouse/apps/console/main.py
safehouse/apps/console/commands/__init__.py
safehouse/apps/console/commands/exceptions.py
safehouse/apps/console/commands/types.py
safehouse/apps/console/commands/orgs/__init__.py
safehouse/apps/console/commands/projects/__init__.py
safehouse/apps/console/commands/projects/init.py
safehouse/apps/console/commands/projects/list_events.py
safehouse/apps/console/commands/services/__init__.py
safehouse/apps/console/commands/services/down.py
safehouse/apps/console/commands/services/up.py
safehouse/apps/console/commands/status/__init__.py
safehouse/apps/console/commands/users/__init__.py
safehouse/apps/console/commands/users/get_attribute.py
safehouse/apps/console/commands/users/set_attribute.py
safehouse/apps/console/commands/version/__init__.py
safehouse/apps/shmake/__init__.py
safehouse/apps/shmake/config.py
safehouse/apps/shmake/main.py
safehouse/apps/shmake/builders/__init__.py
safehouse/apps/shmake/commands/__init__.py
safehouse/apps/shmake/commands/build.py
safehouse/apps/shmake/commands/command.py
safehouse/apps/shmake/commands/configure.py
safehouse/apps/shmake/configurations/__init__.py
safehouse/apps/shmake/configurations/cmake.py
safehouse/apps/shmake/configurations/compilers.py
safehouse/apps/shmake/configurations/platforms.py
safehouse/apps/shmake/configurations/targets.py
safehouse/apps/shmake/projects/__init__.py
safehouse/data/__init__.py
safehouse/data/docker-compose.yaml
safehouse/events/__init__.py
safehouse/events/event.py
safehouse/events/event_manager.py
safehouse/events/exceptions.py
safehouse/projects/__init__.py
safehouse/projects/exceptions.py
safehouse/projects/projects.py
safehouse/services/__init__.py
safehouse/services/assertions.py
safehouse/services/client.py
safehouse/services/exceptions.py
safehouse/services/local.py
safehouse/services/docker_compose/__init__.py
safehouse-0.0.12.dist-info/METADATA
safehouse-0.0.12.dist-info/WHEEL
safehouse-0.0.12.dist-info/entry_points.txt
safehouse-0.0.12.dist-info/top_level.txt
safehouse-0.0.12.dist-info/RECORD
