Metadata-Version: 2.4
Name: safehouse
Version: 0.0.12
Summary: SDK and command line tools from managing the Safehouse game development ecosystem
Author-email: Tim Flechtner <tflecht@gmail.com>
License-Expression: MIT
Classifier: Programming Language :: Python :: 3
Classifier: Operating System :: OS Independent
Requires-Python: >=3.11
Requires-Dist: docker~=7.1
Requires-Dist: ipython~=9.7
Requires-Dist: python-dotenv~=1.2
Requires-Dist: python-on-whales~=0.79
Requires-Dist: requests~=2.32
Requires-Dist: ruff>=0.14.10
